wfgy_sdk/__init__.py
wfgy_sdk/bbam.py
wfgy_sdk/bbcr.py
wfgy_sdk/bbmc.py
wfgy_sdk/bbpf.py
wfgy_sdk/cli.py
wfgy_sdk/evaluator.py
wfgy_sdk/initializer.py
wfgy_sdk/reporter.py
wfgy_sdk/utils.py
wfgy_sdk/visual.py
wfgy_sdk/wfgy_engine.py
wfgy_sdk-1.0.1.dist-info/licenses/LICENSE
wfgy_sdk-1.0.1.dist-info/METADATA
wfgy_sdk-1.0.1.dist-info/WHEEL
wfgy_sdk-1.0.1.dist-info/entry_points.txt
wfgy_sdk-1.0.1.dist-info/top_level.txt
wfgy_sdk-1.0.1.dist-info/RECORD
