Metadata-Version: 2.4
Name: wfgy_sdk
Version: 1.0.1
Summary: WFGY 1.0 • Self-Healing LLM Framework SDK
Home-page: https://github.com/onestardao/WFGY
Author: PSBigBig
Author-email: hello@onestardao.com
Requires-Python: >=3.10
License-File: LICENSE
Requires-Dist: numpy<2.0
Requires-Dist: torch==2.2.2
Requires-Dist: transformers==4.41.2
Requires-Dist: tabulate
Requires-Dist: matplotlib
Dynamic: author
Dynamic: author-email
Dynamic: home-page
Dynamic: license-file
Dynamic: requires-dist
Dynamic: requires-python
Dynamic: summary
